README.rst
setup.py
jw/__init__.py
jw.emerge_update.egg-info/PKG-INFO
jw.emerge_update.egg-info/SOURCES.txt
jw.emerge_update.egg-info/dependency_links.txt
jw.emerge_update.egg-info/entry_points.txt
jw.emerge_update.egg-info/requires.txt
jw.emerge_update.egg-info/top_level.txt
jw/emerge_update/__init__.py
jw/emerge_update/main.py