Metadata-Version: 1.1
Name: jw.emerge-update
Version: 0.4.7
Summary: Package maintenance (portage) and system management for Gentoo Linux
Home-page: https://pypi.python.org/pypi/emerge-update
Author: Johnny Wezel
Author-email: dev-jay@wezel.name
License: GPL
Keywords: gentoo package maintenance
Platform: Linux
Classifier: Development Status :: 5 - Production/Stable
Classifier: Environment :: Console
Classifier: Intended Audience :: Information Technology
Classifier: License :: OSI Approved :: GNU General Public License v3 or later (GPLv3+)
Classifier: Natural Language :: English
Classifier: Operating System :: POSIX :: Linux
Classifier: Programming Language :: Python :: 2.7
Classifier: Programming Language :: Python :: 3.4
